cassandra/__init__.py
cassandra/application_info.py
cassandra/auth.py
cassandra/buffer.pxd
cassandra/bytesio.cpython-312-x86_64-linux-gnu.so
cassandra/bytesio.pxd
cassandra/bytesio.pyx
cassandra/c_shard_info.cpython-312-x86_64-linux-gnu.so
cassandra/c_shard_info.pyx
cassandra/cluster.cpython-312-x86_64-linux-gnu.so
cassandra/cluster.py
cassandra/cmurmur3.c
cassandra/cmurmur3.cpython-312-x86_64-linux-gnu.so
cassandra/concurrent.cpython-312-x86_64-linux-gnu.so
cassandra/concurrent.py
cassandra/connection.cpython-312-x86_64-linux-gnu.so
cassandra/connection.py
cassandra/cqltypes.cpython-312-x86_64-linux-gnu.so
cassandra/cqltypes.py
cassandra/cython_deps.py
cassandra/cython_marshal.cpython-312-x86_64-linux-gnu.so
cassandra/cython_marshal.pyx
cassandra/cython_utils.cpython-312-x86_64-linux-gnu.so
cassandra/cython_utils.pxd
cassandra/cython_utils.pyx
cassandra/deserializers.cpython-312-x86_64-linux-gnu.so
cassandra/deserializers.pxd
cassandra/deserializers.pyx
cassandra/encoder.py
cassandra/ioutils.cpython-312-x86_64-linux-gnu.so
cassandra/ioutils.pyx
cassandra/lwt_info.py
cassandra/marshal.py
cassandra/metadata.cpython-312-x86_64-linux-gnu.so
cassandra/metadata.py
cassandra/metrics.py
cassandra/murmur3.py
cassandra/numpyFlags.h
cassandra/numpy_parser.cpython-312-x86_64-linux-gnu.so
cassandra/numpy_parser.pyx
cassandra/obj_parser.cpython-312-x86_64-linux-gnu.so
cassandra/obj_parser.pyx
cassandra/parsing.cpython-312-x86_64-linux-gnu.so
cassandra/parsing.pxd
cassandra/parsing.pyx
cassandra/policies.py
cassandra/pool.cpython-312-x86_64-linux-gnu.so
cassandra/pool.py
cassandra/protocol.cpython-312-x86_64-linux-gnu.so
cassandra/protocol.py
cassandra/protocol_features.py
cassandra/query.cpython-312-x86_64-linux-gnu.so
cassandra/query.py
cassandra/row_parser.cpython-312-x86_64-linux-gnu.so
cassandra/row_parser.pyx
cassandra/segment.py
cassandra/shard_info.cpython-312-x86_64-linux-gnu.so
cassandra/shard_info.py
scylla_driver-3.29.7.dist-info/METADATA
scylla_driver-3.29.7.dist-info/WHEEL
scylla_driver-3.29.7.dist-info/top_level.txt
scylla_driver-3.29.7.dist-info/RECORD
scylla_driver-3.29.7.dist-info/licenses/LICENSE
