Metadata-Version: 2.4
Name: scylla-driver
Version: 3.29.7
Summary: Scylla Driver for Apache Cassandra
Author: ScyllaDB
License-Expression: Apache-2.0
Project-URL: Homepage, https://github.com/scylladb/python-driver
Project-URL: Documentation, https://scylladb.github.io/python-driver/
Project-URL: Source, https://github.com/scylladb/python-driver/
Project-URL: Issues, https://github.com/scylladb/python-driver/issues
Keywords: cassandra,cql,orm,dse,graph
Classifier: Development Status :: 5 - Production/Stable
Classifier: Intended Audience :: Developers
Classifier: Natural Language :: English
Classifier: Operating System :: OS Independent
Classifier: Programming Language :: Python
Classifier: Programming Language :: Python :: 3.10
Classifier: Programming Language :: Python :: 3.11
Classifier: Programming Language :: Python :: 3.12
Classifier: Programming Language :: Python :: 3.13
Classifier: Programming Language :: Python :: 3.14
Classifier: Programming Language :: Python :: Free Threading :: 2 - Beta
Classifier: Programming Language :: Python :: Implementation :: CPython
Classifier: Programming Language :: Python :: Implementation :: PyPy
Classifier: Topic :: Software Development :: Libraries :: Python Modules
Requires-Python: >=3.9
License-File: LICENSE
Requires-Dist: geomet>=1.1
Requires-Dist: pyyaml>5.0
Provides-Extra: graph
Requires-Dist: gremlinpython==3.7.4; extra == "graph"
Provides-Extra: cle
Requires-Dist: cryptography>=35.0; extra == "cle"
Provides-Extra: compress-lz4
Requires-Dist: lz4; extra == "compress-lz4"
Provides-Extra: compress-snappy
Requires-Dist: python-snappy; extra == "compress-snappy"
Dynamic: license-file
